visiontext/__init__.py
visiontext/__main__.py
visiontext/audiotools.py
visiontext/bboxes.py
visiontext/cacheutils.py
visiontext/colormaps.py
visiontext/configutils.py
visiontext/denormalize.py
visiontext/distutils.py
visiontext/font.py
visiontext/htmltools.py
visiontext/image_downloader.py
visiontext/images.py
visiontext/imports.py
visiontext/mathutils.py
visiontext/pandatools.py
visiontext/plots.py
visiontext/terminal.py
visiontext/torchutils.py
visiontext/visualize_logits.py
visiontext/visualize_ratios.py
visiontext/webdataset_pipeline.py
visiontext/webdataset_pipeline_separate_metadata.py
visiontext/cli/__init__.py
visiontext/cli/collect_env_details.py
visiontext/cli/compare_jpeg_decoder_performance.py
visiontext/cli/download_hf_dataset.py
visiontext/cli/export_sqlite_to_csv.py
visiontext/cli/gui_lib_example.py
visiontext/cli/gui_scroll_example.py
visiontext/cli/index_tar.py
visiontext/cli/profile_gpu.py
visiontext/cli/spek.py
visiontext/cli/start_debugger.py
visiontext/examples/__init__.py
visiontext/examples/cc0images/__init__.py
visiontext/examples/cc0images/lowres/__init__.py
visiontext/gui/__init__.py
visiontext/gui/gui_base.py
visiontext/gui/gui_config.py
visiontext/gui/gui_modules.py
visiontext/gui/message_box.py
visiontext/iotools/__init__.py
visiontext/iotools/feature_compression.py
visiontext/iotools/pth.py
visiontext/iotools/single_tar_lookup.py
visiontext/iotools/tar_lookup.py
visiontext/nlp/__init__.py
visiontext/nlp/lemmatizer.py
visiontext/nlp/nltktools.py
visiontext/nlp/regextools.py
visiontext/nlp/spacytools.py
visiontext/profiling/__init__.py
visiontext/profiling/code_profiler.py
visiontext/profiling/hardware_profiler.py
visiontext/sqlalchemist/__init__.py
visiontext/sqlalchemist/db_opener.py
visiontext/sqlalchemist/sqlalchemist.py
visiontext/testdata/__init__.py
visiontext-0.33.5.dist-info/licenses/LICENSE
visiontext-0.33.5.dist-info/METADATA
visiontext-0.33.5.dist-info/WHEEL
visiontext-0.33.5.dist-info/top_level.txt
visiontext-0.33.5.dist-info/zip-safe
visiontext-0.33.5.dist-info/RECORD
