Metadata-Version: 2.4
Name: visiontext
Version: 0.33.5
Summary: Utilities for deep learning on multimodal data.
Author: simon-ging
License: Apache-2.0
Project-URL: Project-URL, https://github.com/simon-ging/visiontext
Keywords: python,jupyter,notebook,lab,ipython,html,pandas,matplotlib,pytorch,numpy
Platform: any
Classifier: Development Status :: 3 - Alpha
Classifier: Intended Audience :: Developers
Classifier: License :: OSI Approved :: Apache Software License
Classifier: Natural Language :: English
Classifier: Programming Language :: Python :: 3.8
Classifier: Programming Language :: Python :: 3.9
Classifier: Programming Language :: Python :: 3.10
Classifier: Programming Language :: Python :: 3.11
Classifier: Programming Language :: Python :: 3.12
Classifier: Operating System :: OS Independent
Classifier: Topic :: Software Development :: Version Control :: Git
Requires-Python: >=3.8
License-File: LICENSE
Requires-Dist: ipython
Requires-Dist: packg
Requires-Dist: numpy
Requires-Dist: scipy
Requires-Dist: matplotlib
Requires-Dist: seaborn
Requires-Dist: jupyter
Requires-Dist: notebook
Requires-Dist: itables
Requires-Dist: ipdb
Requires-Dist: nltk
Requires-Dist: pandas
Requires-Dist: pyinstrument
Requires-Dist: nvidia-ml-py
Requires-Dist: psutil
Requires-Dist: h5py
Requires-Dist: pillow
Requires-Dist: omegaconf
Requires-Dist: safetensors
Requires-Dist: termcolor
Requires-Dist: chardet
Requires-Dist: spacy; python_version >= "3.10"
Requires-Dist: lmdb
Requires-Dist: msgpack
Requires-Dist: pydub
Provides-Extra: full
Requires-Dist: pyturbojpeg; extra == "full"
Requires-Dist: opencv-python; extra == "full"
Dynamic: license-file
